LICENSE
MANIFEST.in
README.md
setup.cfg
setup.py
otbench/__init__.py
otbench.egg-info/PKG-INFO
otbench.egg-info/SOURCES.txt
otbench.egg-info/dependency_links.txt
otbench.egg-info/requires.txt
otbench.egg-info/top_level.txt
otbench/benchmark/__init__.py
otbench/benchmark/bench_runner.py
otbench/benchmark/models/__init__.py
otbench/benchmark/models/forecasting/__init__.py
otbench/benchmark/models/forecasting/base_model.py
otbench/benchmark/models/forecasting/climatology.py
otbench/benchmark/models/forecasting/gradient_boosting_regression_tree.py
otbench/benchmark/models/forecasting/linear.py
otbench/benchmark/models/forecasting/mean_window.py
otbench/benchmark/models/forecasting/minute_climatology.py
otbench/benchmark/models/forecasting/persistence.py
otbench/benchmark/models/forecasting/pytorch/__init__.py
otbench/benchmark/models/forecasting/pytorch/base_pytorch_model.py
otbench/benchmark/models/forecasting/pytorch/recurrent_neural_network.py
otbench/benchmark/models/regression/__init__.py
otbench/benchmark/models/regression/air_water_temperature_difference.py
otbench/benchmark/models/regression/base_model.py
otbench/benchmark/models/regression/climatology.py
otbench/benchmark/models/regression/gradient_boosting_regression_tree.py
otbench/benchmark/models/regression/hybrid_awt.py
otbench/benchmark/models/regression/macro_meteorological.py
otbench/benchmark/models/regression/minute_climatology.py
otbench/benchmark/models/regression/offshore_macro_meteorological.py
otbench/benchmark/models/regression/persistence.py
otbench/benchmark/models/regression/pytorch/__init__.py
otbench/benchmark/models/regression/pytorch/base_pytorch_model.py
otbench/benchmark/models/regression/pytorch/recurrent_neural_network.py
otbench/cache/__init__.py
otbench/cache/memcache.py
otbench/config/__init__.py
otbench/config/config.py
otbench/dataset/__init__.py
otbench/dataset/dataset.py
otbench/eval/__init__.py
otbench/eval/metrics.py
otbench/plot/__init__.py
otbench/plot/timeseries.py
otbench/tasks/__init__.py
otbench/tasks/tasks.py
otbench/utils/__init__.py
otbench/utils/height_adjustment.py
otbench/utils/solar_features.py