Metadata-Version: 2.1
Name: otbench
Version: 0.24.1.7.1
Summary: Consistent benchmarks for evaluating optical turbulence strength models.
Home-page: https://github.com/cdjellen/otbench
Download-URL: https://github.com/cdjellen/otbench/tarball/main
Author: Chris Jellen
Author-email: cdjellen@gmail.com
License: MIT
Keywords: optics,turbulence,benchmark,python3
Classifier: Development Status :: 5 - Production/Stable
Classifier: Intended Audience :: Developers
Classifier: License :: OSI Approved :: MIT License
Classifier: Programming Language :: Python :: 3.9
Classifier: Programming Language :: Python :: 3.10
Classifier: Programming Language :: Python :: 3.11
License-File: LICENSE
Requires-Dist: astral
Requires-Dist: pandas
Requires-Dist: requests
Requires-Dist: scikit-learn
Requires-Dist: xarray
